{
    "type":  "jazzycookin:kitchen_process",
    "station":  "mixing_bowl",
    "inputs":  [
                   {
                       "ingredient":  {
                                          "item":  "jazzycookin:all_purpose_flour"
                                      },
                       "required_state":  "all_purpose_flour"
                   },
                   {
                       "ingredient":  {
                                          "tag":  "jazzycookin:salts"
                                      },
                       "required_state":  "pantry_ready"
                   }
               ],
    "duration":  40,
    "outcomes":  [
                     {
                         "band":  "under",
                         "output":  {
                                        "result":  {
                                                       "id":  "jazzycookin:fish_coating",
                                                       "count":  1
                                                   },
                                        "state":  "coarse_powder"
                                    }
                     },
                     {
                         "band":  "over",
                         "output":  {
                                        "result":  {
                                                       "id":  "jazzycookin:fish_coating",
                                                       "count":  1
                                                   },
                                        "state":  "fine_powder"
                                    }
                     }
                 ],
    "output":  {
                   "result":  {
                                  "id":  "jazzycookin:fish_coating",
                                  "count":  1
                              },
                   "state":  "mixed"
               },
    "recipe_book":  {
                        "chain_key":  "fried_fish"
                    }
}
