{
    "type":  "jazzycookin:kitchen_plate",
    "inputs":  [
                   {
                       "ingredient":  {
                                          "item":  "jazzycookin:fried_fish_prep"
                                      },
                       "required_state":  "rested"
                   },
                   {
                       "ingredient":  {
                                          "item":  "jazzycookin:ceramic_plate"
                                      },
                       "required_state":  "pantry_ready"
                   },
                   {
                       "ingredient":  {
                                          "item":  "jazzycookin:lemons"
                                      },
                       "required_state":  "lemons"
                   }
               ],
    "output":  {
                   "result":  {
                                  "id":  "jazzycookin:fried_fish",
                                  "count":  1
                              },
                   "state":  "plated_fried_meal"
               },
    "recipe_book":  {
                        "chain_key":  "fried_fish"
                    }
}
